{
"type": "FeatureCollection",
"name": "Ecoles",
"crs": { "type": "name", "properties": { "name": "urn:ogc:def:crs:OGC:1.3:CRS84" } },
"features": [
{ "type": "Feature", "properties": { "OBJECTID": 9, "osm_id": "5312130321", "code": 2082, "fclass": "school", "name": "Doudal fass gounass" }, "geometry": { "type": "Point", "coordinates": [ -14.522488099646012, 14.046045299550997 ] } },
{ "type": "Feature", "properties": { "OBJECTID": 17, "osm_id": "6992266087", "code": 2082, "fclass": "school", "name": "DUDAL NADIACI" }, "geometry": { "type": "Point", "coordinates": [ -14.524925399987183, 14.043184000341398 ] } }
]
}
